MarkdownZhinanFix1/README.md
MarkdownZhinanFix1/__init__.py
MarkdownZhinanFix1/__main__.py
MarkdownZhinanFix1/file.epub
MarkdownZhinanFix1/index.html
MarkdownZhinanFix1/css/__init__.py
MarkdownZhinanFix1/css/annotations.css
MarkdownZhinanFix1/css/main.css
MarkdownZhinanFix1/css/normalize.css
MarkdownZhinanFix1/css/popup.css
MarkdownZhinanFix1/font/__init__.py
MarkdownZhinanFix1/font/fontello.eot
MarkdownZhinanFix1/font/fontello.svg
MarkdownZhinanFix1/font/fontello.ttf
MarkdownZhinanFix1/font/fontello.woff
MarkdownZhinanFix1/img/__init__.py
MarkdownZhinanFix1/img/annotator-glyph-sprite.png
MarkdownZhinanFix1/img/annotator-icon-sprite.png
MarkdownZhinanFix1/img/apple-touch-icon.png
MarkdownZhinanFix1/img/cancelfullscreen.png
MarkdownZhinanFix1/img/close.png
MarkdownZhinanFix1/img/fullscreen.png
MarkdownZhinanFix1/img/loader.gif
MarkdownZhinanFix1/img/menu-icon.png
MarkdownZhinanFix1/img/save.png
MarkdownZhinanFix1/img/saved.png
MarkdownZhinanFix1/img/settings-s.png
MarkdownZhinanFix1/img/settings.png
MarkdownZhinanFix1/img/star.png
MarkdownZhinanFix1/js/__init__.py
MarkdownZhinanFix1/js/epub.js
MarkdownZhinanFix1/js/epub.min.js
MarkdownZhinanFix1/js/epub.min.map
MarkdownZhinanFix1/js/hooks.min.js
MarkdownZhinanFix1/js/hooks.min.map
MarkdownZhinanFix1/js/reader.js
MarkdownZhinanFix1/js/reader.js.map
MarkdownZhinanFix1/js/reader.min.js
MarkdownZhinanFix1/js/reader.min.map
MarkdownZhinanFix1/js/hooks/__init__.py
MarkdownZhinanFix1/js/hooks/extensions/__init__.py
MarkdownZhinanFix1/js/hooks/extensions/highlight.js
MarkdownZhinanFix1/js/libs/__init__.py
MarkdownZhinanFix1/js/libs/jquery.min.js
MarkdownZhinanFix1/js/libs/localforage.min.js
MarkdownZhinanFix1/js/libs/screenfull.js
MarkdownZhinanFix1/js/libs/screenfull.min.js
MarkdownZhinanFix1/js/libs/zip.min.js
MarkdownZhinanFix1/js/plugins/__init__.py
MarkdownZhinanFix1/js/plugins/hypothesis.js
MarkdownZhinanFix1/js/plugins/search.js
markdown_zhinan_fix1-2025.3.25.1.dist-info/METADATA
markdown_zhinan_fix1-2025.3.25.1.dist-info/WHEEL
markdown_zhinan_fix1-2025.3.25.1.dist-info/entry_points.txt
markdown_zhinan_fix1-2025.3.25.1.dist-info/top_level.txt
markdown_zhinan_fix1-2025.3.25.1.dist-info/RECORD
